pysondb/__init__.py
pysondb/cli.py
pysondb/db.py
pysondb/errors/__init__.py
pysondb/errors/db_errors.py
tests/__init__.py
pysondb-1.6.7.dist-info/LICENSE
pysondb-1.6.7.dist-info/METADATA
pysondb-1.6.7.dist-info/WHEEL
pysondb-1.6.7.dist-info/entry_points.txt
pysondb-1.6.7.dist-info/top_level.txt
pysondb-1.6.7.dist-info/RECORD
