Metadata-Version: 2.1
Name: pysondb
Version: 1.6.7
Summary: A Python JSON based lightweight Database.
Home-page: https://github.com/pysonDB/pysonDB
Author: Fredy Somy
Author-email: fredysomy@gmail.com
License: MIT License
Keywords: pysondb,database,json
Platform: UNKNOWN
Classifier: Development Status :: 2 - Pre-Alpha
Classifier: License :: OSI Approved :: MIT License
Classifier: Natural Language :: English
Classifier: Programming Language :: Python :: 3
Requires-Python: >=3
License-File: LICENSE
